Metadata-Version: 2.1
Name: odoo11-addon-github-connector-odoo
Version: 11.0.1.2.1
Summary: Analyze Odoo modules information from Github repositories
Home-page: UNKNOWN
Author: Odoo Community Association (OCA), Sylvain LE GAL, GRAP
Author-email: support@odoo-community.org
License: AGPL-3
Platform: UNKNOWN
Classifier: Programming Language :: Python
Classifier: Framework :: Odoo
Classifier: License :: OSI Approved :: GNU Affero General Public License v3
Requires-Python: >=2.7, !=3.0.*, !=3.1.*, !=3.2.*, !=3.3.*, !=3.4.*
Requires-Dist: odoo11-addon-github-connector
Requires-Dist: odoo (<11.1dev,>=11.0a)
